django5_scheduler-1.0.2.dist-info/licenses/LICENSE.txt
schedule/__init__.py
schedule/admin.py
schedule/apps.py
schedule/forms.py
schedule/periods.py
schedule/settings.py
schedule/urls.py
schedule/utils.py
schedule/views.py
schedule/widgets.py
schedule/feeds/__init__.py
schedule/feeds/ical.py
schedule/locale/de/LC_MESSAGES/django.mo
schedule/locale/de/LC_MESSAGES/django.po
schedule/locale/en/LC_MESSAGES/django.mo
schedule/locale/en/LC_MESSAGES/django.po
schedule/locale/es/LC_MESSAGES/django.mo
schedule/locale/es/LC_MESSAGES/django.po
schedule/locale/fi/LC_MESSAGES/django.mo
schedule/locale/fi/LC_MESSAGES/django.po
schedule/locale/fr/LC_MESSAGES/django.mo
schedule/locale/fr/LC_MESSAGES/django.po
schedule/locale/it/LC_MESSAGES/django.mo
schedule/locale/it/LC_MESSAGES/django.po
schedule/locale/pt_BR/LC_MESSAGES/django.mo
schedule/locale/pt_BR/LC_MESSAGES/django.po
schedule/locale/ru/LC_MESSAGES/django.mo
schedule/locale/ru/LC_MESSAGES/django.po
schedule/locale/zh/LC_MESSAGES/django.mo
schedule/locale/zh/LC_MESSAGES/django.po
schedule/migrations/0001_initial.py
schedule/migrations/0002_event_color_event.py
schedule/migrations/0003_auto_20160715_0028.py
schedule/migrations/0004_text_fields_not_null.py
schedule/migrations/0005_verbose_name_plural_for_calendar.py
schedule/migrations/0006_update_text_fields_empty_string.py
schedule/migrations/0007_merge_text_fields.py
schedule/migrations/0008_gfk_index.py
schedule/migrations/0009_merge_20180108_2303.py
schedule/migrations/0010_events_set_missing_calendar.py
schedule/migrations/0011_event_calendar_not_null.py
schedule/migrations/0012_auto_20191025_1852.py
schedule/migrations/0013_auto_20210502_2303.py
schedule/migrations/0014_use_autofields_for_pk.py
schedule/migrations/0015_rename_calendarrelation_content_type_object_id_schedule_ca_content_cddadb_idx_and_more.py
schedule/migrations/__init__.py
schedule/models/__init__.py
schedule/models/calendars.py
schedule/models/events.py
schedule/models/rules.py
schedule/static/schedule.css
schedule/static/schedule.js
django5_scheduler-1.0.2.dist-info/METADATA
django5_scheduler-1.0.2.dist-info/WHEEL
django5_scheduler-1.0.2.dist-info/top_level.txt
django5_scheduler-1.0.2.dist-info/RECORD
