Metadata-Version: 2.4
Name: django5-scheduler
Version: 1.0.2
Summary: A calendaring app for Django5 (forked from orginal django-scheduler source).
Home-page: https://github.com/NCIAdmin/django5-scheduler
Author: Leonardo Lazzaro updated by Jake Morgan at NCI
Author-email: lazzaroleonardo@gmail.com | updated by: jmorgan@ncicap.org
License: BSD
Classifier: Development Status :: 5 - Production/Stable
Classifier: Environment :: Web Environment
Classifier: Framework :: Django
Classifier: Framework :: Django :: 5.2
Classifier: Intended Audience :: Developers
Classifier: License :: OSI Approved :: BSD License
Classifier: Operating System :: OS Independent
Classifier: Programming Language :: Python
Classifier: Programming Language :: Python :: 3
Classifier: Programming Language :: Python :: 3 :: Only
Classifier: Programming Language :: Python :: 3.7
Classifier: Programming Language :: Python :: 3.8
Classifier: Programming Language :: Python :: 3.9
Classifier: Programming Language :: Python :: 3.10
Classifier: Programming Language :: Python :: 3.11
Classifier: Programming Language :: Python :: 3.12
Classifier: Programming Language :: Python :: 3.13
Classifier: Topic :: Utilities
Requires-Python: >=3.7
License-File: LICENSE.txt
Requires-Dist: Django>=5.0
Requires-Dist: python-dateutil>=2.1
Requires-Dist: pytz>=2013.9
Requires-Dist: icalendar>=3.8.4
Provides-Extra: dev
Requires-Dist: black; extra == "dev"
Requires-Dist: coverage>=3.7.1; extra == "dev"
Requires-Dist: flake8; extra == "dev"
Requires-Dist: isort; extra == "dev"
Dynamic: license-file
